digital/template/src/counter.v
module counter (
    input  wire       clk,
    input  wire       rst_n,
    input  wire       enable,
    output reg  [7:0] count,
    output wire       overflow
);

  always @(posedge clk or negedge rst_n) begin
    if (!rst_n) begin
      count <= 8'b0;
    end else if (enable) begin
      count <= count + 1'b1;
    end
  end

  assign overflow = (count == 8'hFF) && enable;

endmodule

digital/test/tb_counter.v
`timescale 1ns / 1ps

module tb_counter;

  // Testbench signals
  reg        clk;
  reg        rst_n;
  reg        enable;
  wire [7:0] count;
  wire       overflow;

  // Clock generation
  initial begin
    clk = 0;
    forever #5 clk = ~clk;  // 100MHz clock (10ns period)
  end

  // DUT instantiation
  counter dut (
      .clk(clk),
      .rst_n(rst_n),
      .enable(enable),
      .count(count),
      .overflow(overflow)
  );

  // Test stimulus
  initial begin
    // Initialize signals
    rst_n  = 0;
    enable = 0;

    // Wait for a few clock cycles
    repeat (3) @(posedge clk);

    // Release reset
    rst_n = 1;
    @(posedge clk);

    // Test 1: Basic counting
    $display("=== Test 1: Basic Counting ===");
    enable = 1;
    repeat (10) begin
      @(posedge clk);
      $display("Time: %0t, Count: %d, Overflow: %b", $time, count, overflow);
    end

    // Test 2: Disable counting
    $display("\n=== Test 2: Disable Counting ===");
    enable = 0;
    repeat (5) begin
      @(posedge clk);
      $display("Time: %0t, Count: %d, Overflow: %b", $time, count, overflow);
    end

    // Test 3: Resume counting
    $display("\n=== Test 3: Resume Counting ===");
    enable = 1;
    repeat (5) begin
      @(posedge clk);
      $display("Time: %0t, Count: %d, Overflow: %b", $time, count, overflow);
    end

    // Test 4: Test overflow
    $display("\n=== Test 4: Test Overflow ===");
    // Set counter close to overflow
    @(posedge clk);
    force dut.count = 8'hFD;  // Force count to 253
    @(posedge clk);
    release dut.count;

    repeat (5) begin
      @(posedge clk);
      $display("Time: %0t, Count: %d (0x%02h), Overflow: %b", $time, count, count, overflow);
    end

    // Test 5: Reset during counting
    $display("\n=== Test 5: Reset During Counting ===");
    rst_n = 0;
    @(posedge clk);
    $display("Time: %0t, Count: %d, Overflow: %b (After Reset)", $time, count, overflow);

    rst_n = 1;
    @(posedge clk);
    $display("Time: %0t, Count: %d, Overflow: %b (After Reset Release)", $time, count, overflow);

    // Test 6: Overflow behavior
    $display("\n=== Test 6: Continuous Overflow Test ===");
    enable = 1;
    repeat (20) begin
      @(posedge clk);
      if (overflow) begin
        $display("Time: %0t, OVERFLOW! Count: %d", $time, count);
      end
    end

    $display("\n=== All Tests Completed ===");
    $finish;
  end

  // Monitor for unexpected behavior
  always @(posedge clk) begin
    if (rst_n) begin
      // Check that count doesn't exceed 8-bit range
      if (count > 255) begin
        $error("ERROR: Count exceeded 8-bit range: %d", count);
      end

      // Check overflow logic
      if (overflow && (count != 8'hFF || !enable)) begin
        $error("ERROR: Overflow asserted incorrectly. Count: %d, Enable: %b", count, enable);
      end

      if (!overflow && count == 8'hFF && enable) begin
        $error("ERROR: Overflow should be asserted. Count: %d, Enable: %b", count, enable);
      end
    end
  end

  // Optional: Generate VCD file for waveform viewing
  initial begin
    $dumpfile("counter_tb.vcd");
    $dumpvars(0, tb_counter);
  end

endmodule

digital/template/build/des_tb/simulations/counter_tb.vcd
$date
	Fri Jun 27 11:49:27 2025
$end
$version
	Icarus Verilog
$end
$timescale
	1ps
$end
$scope module tb_counter $end
$var wire 1 ! overflow $end
$var wire 8 " count [7:0] $end
$var reg 1 # clk $end
$var reg 1 $ enable $end
$var reg 1 % rst_n $end
$scope module dut $end
$var wire 1 # clk $end
$var wire 1 $ enable $end
$var wire 1 ! overflow $end
$var wire 1 % rst_n $end
$var reg 8 & count [7:0] $end
$upscope $end
$upscope $end
$enddefinitions $end
$comment Show the parameter values. $end
$dumpall
$end
#0
$dumpvars
b0 &
0%
0$
0#
b0 "
0!
$end
#5000
1#
#10000
0#
#15000
1#
#20000
0#
#25000
1%
1#
#30000
0#
#35000
b1 "
b1 &
1$
1#
#40000
0#
#45000
b10 "
b10 &
1#
#50000
0#
#55000
b11 "
b11 &
1#
#60000
0#
#65000
b100 "
b100 &
1#
#70000
0#
#75000
b101 "
b101 &
1#
#80000
0#
#85000
b110 "
b110 &
1#
#90000
0#
#95000
b111 "
b111 &
1#
#100000
0#
#105000
b1000 "
b1000 &
1#
#110000
0#
#115000
b1001 "
b1001 &
1#
#120000
0#
#125000
b1010 "
b1010 &
1#
#130000
0#
#135000
0$
1#
#140000
0#
#145000
1#
#150000
0#
#155000
1#
#160000
0#
#165000
1#
#170000
0#
#175000
1#
#180000
0#
#185000
b1011 "
b1011 &
1$
1#
#190000
0#
#195000
b1100 "
b1100 &
1#
#200000
0#
#205000
b1101 "
b1101 &
1#
#210000
0#
#215000
b1110 "
b1110 &
1#
#220000
0#
#225000
b1111 "
b1111 &
1#
#230000
0#
#235000
b10000 "
b10000 &
1#
#240000
0#
#245000
b11111101 "
b11111101 &
1#
#250000
0#
#255000
b11111110 "
b11111110 &
1#
#260000
0#
#265000
1!
b11111111 "
b11111111 &
1#
#270000
0#
#275000
0!
b0 "
b0 &
1#
#280000
0#
#285000
b1 "
b1 &
1#
#290000
0#
#295000
b10 "
b10 &
1#
#300000
0#
#305000
b0 "
b0 &
0%
1#
#310000
0#
#315000
b1 "
b1 &
1%
1#
#320000
0#
#325000
b10 "
b10 &
1#
#330000
0#
#335000
b11 "
b11 &
1#
#340000
0#
#345000
b100 "
b100 &
1#
#350000
0#
#355000
b101 "
b101 &
1#
#360000
0#
#365000
b110 "
b110 &
1#
#370000
0#
#375000
b111 "
b111 &
1#
#380000
0#
#385000
b1000 "
b1000 &
1#
#390000
0#
#395000
b1001 "
b1001 &
1#
#400000
0#
#405000
b1010 "
b1010 &
1#
#410000
0#
#415000
b1011 "
b1011 &
1#
#420000
0#
#425000
b1100 "
b1100 &
1#
#430000
0#
#435000
b1101 "
b1101 &
1#
#440000
0#
#445000
b1110 "
b1110 &
1#
#450000
0#
#455000
b1111 "
b1111 &
1#
#460000
0#
#465000
b10000 "
b10000 &
1#
#470000
0#
#475000
b10001 "
b10001 &
1#
#480000
0#
#485000
b10010 "
b10010 &
1#
#490000
0#
#495000
b10011 "
b10011 &
1#
#500000
0#
#505000
b10100 "
b10100 &
1#
#510000
0#
#515000
b10101 "
b10101 &
1#
#520000
0#
#525000
b10110 "
b10110 &
1#
